coinstac/__init__.py
coinstac-0.2.0.dist-info/METADATA
coinstac-0.2.0.dist-info/WHEEL
coinstac-0.2.0.dist-info/top_level.txt
coinstac-0.2.0.dist-info/RECORD
